test_jx/__init__.py
test_jx/test_jx.py
test_jx-0.0.2.dist-info/LICENSE.txt
test_jx-0.0.2.dist-info/METADATA
test_jx-0.0.2.dist-info/WHEEL
test_jx-0.0.2.dist-info/top_level.txt
test_jx-0.0.2.dist-info/RECORD
