Metadata-Version: 2.1
Name: test-jx
Version: 0.0.2
Summary: used to describe uncertainty in financial data
Home-page: https://github.com/XuanLyu/SLE
Author: Xuan Ji
Author-email: jixuan_1021@163.com
License: MIT
Platform: UNKNOWN
Requires-Python: >=3.6
